vizmath/__init__.py
vizmath/beeswarm.py
vizmath/crystal_bar_chart.py
vizmath/draw.py
vizmath/functions.py
vizmath/multichord_diagram.py
vizmath/path_swarm.py
vizmath/quadtile_chart.py
vizmath/radial_treemap.py
vizmath/stream_chart.py
vizmath/tests.py
vizmath-0.0.47.dist-info/LICENSE
vizmath-0.0.47.dist-info/METADATA
vizmath-0.0.47.dist-info/WHEEL
vizmath-0.0.47.dist-info/top_level.txt
vizmath-0.0.47.dist-info/RECORD
