Metadata-Version: 2.1
Name: vizmath
Version: 0.0.47
Summary: Visualization math toolkit.
Home-page: https://github.com/nickgerend/vizmath
Author: Nick Gerend
Author-email: nickgerend@gmail.com
License: MIT
Classifier: Programming Language :: Python :: 3.9
Classifier: License :: OSI Approved :: MIT License
License-File: LICENSE
Requires-Dist: numpy
Requires-Dist: scipy
Requires-Dist: matplotlib
Requires-Dist: pandas
